saludador/__init__.py
saludador/launcher/__author__.py
saludador/launcher/__init__.py
saludador/launcher/__main__.py
saludador/launcher/__version__.py
saludador/modules/__init__.py
saludador/modules/examples/__init__.py
saludador/modules/examples/__version__.py
saludador/modules/examples/saludador.py
saludador/modules/updater/__init__.py
saludador/modules/updater/spinner.py
saludador/modules/updater/update.py
saludador/resources/__init__.py
saludador-0.0.5.dist-info/LICENSE
saludador-0.0.5.dist-info/METADATA
saludador-0.0.5.dist-info/WHEEL
saludador-0.0.5.dist-info/entry_points.txt
saludador-0.0.5.dist-info/top_level.txt
saludador-0.0.5.dist-info/RECORD
