Metadata-Version: 2.1
Name: saludador
Version: 0.0.5
Summary: Paquete de pruebas para subir a PyPi
Home-page: https://github.com/jaimefeldman/saludador
Author: Jaime Andrés Feldman
Author-email: jaimefel@gmail.com
License: MIT
Classifier: License :: OSI Approved :: MIT License
Classifier: Programming Language :: Python :: 3.10
Classifier: Operating System :: OS Independent
Requires-Python: >=3.10
License-File: LICENSE
Requires-Dist: rich >=13.5.3
Requires-Dist: progress >=1.6
Requires-Dist: requests >=2.31.0
Requires-Dist: cursor >=1.3.5
Requires-Dist: readchar >=4.0.5
Provides-Extra: dev
Requires-Dist: pytest >=7.0 ; extra == 'dev'
Requires-Dist: twine >=4.0.2 ; extra == 'dev'
